calais/__init__.py
calais/chat.py
calais/client.py
calais/content_printer.py
calais/main.py
calais/response.py
calais/system_prompt.py
pycalais-1.0.1.dist-info/LICENSE
pycalais-1.0.1.dist-info/METADATA
pycalais-1.0.1.dist-info/WHEEL
pycalais-1.0.1.dist-info/entry_points.txt
pycalais-1.0.1.dist-info/top_level.txt
pycalais-1.0.1.dist-info/RECORD
