Metadata-Version: 2.1
Name: pycalais
Version: 1.0.1
Summary: Fast shell command generation using GPT-4
Author-email: Gary Boone <gary.boone@gmail.com>
License: Apache License
Project-URL: Homepage, http://github.com/garyboone/calais
Keywords: AI,GPT-4,CLI
License-File: LICENSE
Requires-Dist: openai >=0.10.2
Requires-Dist: typing-extensions ; python_version < "3.8"
